pycalima/Calima.py
pycalima/__init__.py
pycalima/cmdline.py
CalimaCalima2-2.0.2.dist-info/LICENSE
CalimaCalima2-2.0.2.dist-info/METADATA
CalimaCalima2-2.0.2.dist-info/WHEEL
CalimaCalima2-2.0.2.dist-info/entry_points.txt
CalimaCalima2-2.0.2.dist-info/top_level.txt
CalimaCalima2-2.0.2.dist-info/RECORD
